pconn/__init__.py
pconn/__main__.py
pconn/const.py
pconn/core.py
pconn/exceptions.py
pconn/frontend/index.html
pconn/frontend/static/checkbox-BkclbYif.js
pconn/frontend/static/checkbox-validator-DMPvRaTX.js
pconn/frontend/static/dialog-data-entry-flow-CRDLozaz.js
pconn/frontend/static/dynamic-element-directive-D2vSgiS1.js
pconn/frontend/static/ensure-array-ILKxE5fq.js
pconn/frontend/static/filled-button-B0GLItPe.js
pconn/frontend/static/filled-text-field-TyRfCCdN.js
pconn/frontend/static/flow-D-0MTYCm.js
pconn/frontend/static/format_date_time-CG_oC5lZ.js
pconn/frontend/static/index-B4ls59Y5.js
pconn/frontend/static/memoize-one.esm-DezIwejE.js
pconn/frontend/static/menu-Jr98PvdJ.js
pconn/frontend/static/outlined-text-field-BGwQFySR.js
pconn/frontend/static/pc-add-plugin-hlZAUAtI.js
pconn/frontend/static/pc-button-menu-4kLxi82q.js
pconn/frontend/static/pc-circular-progress-Bdgl2OsW.js
pconn/frontend/static/pc-expansion-panel-3kiRKGtk.js
pconn/frontend/static/pc-file-upload-Blk0KRs3.js
pconn/frontend/static/pc-form-CR2TQCX3.js
pconn/frontend/static/pc-label-ltFL3u-e.js
pconn/frontend/static/pc-license-DxMj2WyV.js
pconn/frontend/static/pc-logs-Dqg-E63g.js
pconn/frontend/static/pc-plugin-DUvIe24k.js
pconn/frontend/static/pc-plugin-gallagher_ai_analyzer-s214-Wec.js
pconn/frontend/static/pc-plugin-gallagher_bacnet_emulator-mXukeJsu.js
pconn/frontend/static/pc-plugin-gallagher_demo-YbWTVUIt.js
pconn/frontend/static/pc-plugin-gallagher_odoo-ZRHZHlO_.js
pconn/frontend/static/pc-plugins-mPwIjD7D.js
pconn/frontend/static/pc-select-DS2OqIvJ.js
pconn/frontend/static/pc-selector-boolean-CAb-30jG.js
pconn/frontend/static/pc-selector-file-CrtZ5YdX.js
pconn/frontend/static/pc-selector-number-a4bdiTCq.js
pconn/frontend/static/pc-selector-select-6UGhSV7D.js
pconn/frontend/static/pc-selector-text-CAR0EoSO.js
pconn/frontend/static/pc-setting-Dh4m9w6X.js
pconn/frontend/static/pc-settings-DnOp7SS6.js
pconn/frontend/static/pc-settings-plugins-ClEkrUc_.js
pconn-0.1.0.dist-info/entry_points.txt
pconn-0.1.0.dist-info/METADATA
pconn-0.1.0.dist-info/WHEEL
pconn-0.1.0.dist-info/RECORD
