Metadata-Version: 2.1
Name: pconn
Version: 0.1.0
Summary: Platform Connectors that can interface different platforms to provide specific services.
License: MIT
Author: Rami Mousleh
Requires-Python: >=3.11,<4.0
Classifier: License :: OSI Approved :: MIT License
Classifier: Programming Language :: Python :: 3
Classifier: Programming Language :: Python :: 3.11
Classifier: Programming Language :: Python :: 3.12
Requires-Dist: async-timeout (>=4.0.2,<5.0.0)
Requires-Dist: awesomeversion (>=23.8.0,<24.0.0)
Requires-Dist: cryptography (>=42.0.7,<43.0.0)
Requires-Dist: fastapi[all] (>=0.115.6,<0.116.0)
Requires-Dist: packaging (>=24.0,<25.0)
Requires-Dist: rsa (>=4.9,<5.0)
Requires-Dist: ulid-transform (>=1.0.2,<2.0.0)
Requires-Dist: uvicorn (>=0.29.0,<0.30.0)
Requires-Dist: voluptuous (>=0.13.1,<0.14.0)
Requires-Dist: voluptuous-serialize (>=2.6.0,<3.0.0)
